zdata/__init__.py
zdata/_settings.py
zdata/setup.py
zdata/build_zdata/__init__.py
zdata/build_zdata/align_mtx.py
zdata/build_zdata/build_x.py
zdata/build_zdata/build_zdata.py
zdata/build_zdata/check_directory.py
zdata/build_zdata/concat_obs.py
zdata/core/__init__.py
zdata/core/index.py
zdata/core/utils.py
zdata/core/zdata.py
zdata/ctools/mtx_to_zdata
zdata/ctools/mtx_to_zdata.c
zdata/ctools/zdata_read
zdata/ctools/zdata_read.c
zdata/files/2ks10c_genes.txt
zdata/files/__init__.py
zdata_py-0.1.3.dist-info/licenses/LICENSE
zdata_py-0.1.3.dist-info/METADATA
zdata_py-0.1.3.dist-info/WHEEL
zdata_py-0.1.3.dist-info/top_level.txt
zdata_py-0.1.3.dist-info/RECORD
